mcp_server_omi/__about__.py
mcp_server_omi/__init__.py
mcp_server_omi/__main__.py
mcp_server_omi/server.py
mcp_server_omi-0.1.5.dist-info/METADATA
mcp_server_omi-0.1.5.dist-info/WHEEL
mcp_server_omi-0.1.5.dist-info/entry_points.txt
mcp_server_omi-0.1.5.dist-info/licenses/LICENSE
mcp_server_omi-0.1.5.dist-info/RECORD
