Metadata-Version: 2.4
Name: mcp-server-omi
Version: 0.1.5
Summary: Model Context Protocol Server for Omi AI
Author-email: Joan Cabezas <joan.santiago.cabezas@gmail.com>
License-Expression: MIT
License-File: LICENSE
Keywords: mcp,omi
Classifier: Development Status :: 4 - Beta
Classifier: Intended Audience :: Developers
Classifier: License :: OSI Approved :: MIT License
Classifier: Programming Language :: Python :: 3.11
Classifier: Programming Language :: Python :: 3.12
Requires-Python: >=3.11.6
Requires-Dist: click>=8.1.7
Requires-Dist: mcp[cli]>=1.0.0
Requires-Dist: pydantic>=2.0.0
Requires-Dist: requests>=2.32.3
